pytyped_curry/__init__.py
pytyped_curry/_curry.py
pytyped_curry/_curry_3_11.py
pytyped_curry/_curry_3_7.py
pytyped_curry/_curry_3_8.py
pytyped_curry/_decorator.py
pytyped_curry/_doc.py
pytyped_curry-1.0.3.dist-info/LICENSE
pytyped_curry-1.0.3.dist-info/METADATA
pytyped_curry-1.0.3.dist-info/WHEEL
pytyped_curry-1.0.3.dist-info/top_level.txt
pytyped_curry-1.0.3.dist-info/RECORD
